data_processing_ray/runtime/ray/__init__.py
data_processing_ray/runtime/ray/execution_configuration.py
data_processing_ray/runtime/ray/ray_utils.py
data_processing_ray/runtime/ray/runtime_configuration.py
data_processing_ray/runtime/ray/transform_file_processor.py
data_processing_ray/runtime/ray/transform_invoker.py
data_processing_ray/runtime/ray/transform_launcher.py
data_processing_ray/runtime/ray/transform_orchestrator.py
data_processing_ray/runtime/ray/transform_runtime.py
data_processing_ray/runtime/ray/transform_statistics.py
data_processing_ray/test_support/transform/__init__.py
data_processing_ray/test_support/transform/noop_transform.py
data_prep_toolkit_ray-0.2.1.dist-info/METADATA
data_prep_toolkit_ray-0.2.1.dist-info/WHEEL
data_prep_toolkit_ray-0.2.1.dist-info/top_level.txt
data_prep_toolkit_ray-0.2.1.dist-info/RECORD
