Metadata-Version: 2.1
Name: data_prep_toolkit_ray
Version: 0.2.1
Summary: Data Preparation Toolkit Library for Ray
Author-email: David Wood <dawood@us.ibm.com>, Boris Lublinsky <blublinsky@ibm.com>
License: Apache-2.0
Keywords: data,data preprocessing,data preparation,llm,generative,ai,fine-tuning,llmapps
Requires-Python: >=3.10
Requires-Dist: data-prep-toolkit>=0.2.1
Requires-Dist: ray[default]==2.24.0
Requires-Dist: fastapi>=0.110.2
Requires-Dist: pillow>=10.3.0
Provides-Extra: dev
Requires-Dist: twine; extra == "dev"
Requires-Dist: pytest>=7.3.2; extra == "dev"
Requires-Dist: pytest-dotenv>=0.5.2; extra == "dev"
Requires-Dist: pytest-env>=1.0.0; extra == "dev"
Requires-Dist: pre-commit>=3.3.2; extra == "dev"
Requires-Dist: pytest-cov>=4.1.0; extra == "dev"
Requires-Dist: pytest-mock>=3.10.0; extra == "dev"
Requires-Dist: moto==5.0.5; extra == "dev"
Requires-Dist: markupsafe==2.0.1; extra == "dev"
